{
  "dataset_revision": "09698e0180d87dc247ca447d3a1248b931ac0cdb",
  "task_name": "XNLI",
  "mteb_version": "1.38.46",
  "scores": {
    "test": [
      {
        "similarity_accuracy": 0.642491,
        "similarity_accuracy_threshold": 0.880257,
        "similarity_f1": 0.703911,
        "similarity_f1_threshold": 0.836695,
        "similarity_precision": 0.568592,
        "similarity_recall": 0.923754,
        "similarity_ap": 0.673373,
        "cosine_accuracy": 0.642491,
        "cosine_accuracy_threshold": 0.880257,
        "cosine_f1": 0.703911,
        "cosine_f1_threshold": 0.836695,
        "cosine_precision": 0.568592,
        "cosine_recall": 0.923754,
        "cosine_ap": 0.673373,
        "manhattan_accuracy": 0.642491,
        "manhattan_accuracy_threshold": 11.089812,
        "manhattan_f1": 0.704558,
        "manhattan_f1_threshold": 12.556774,
        "manhattan_precision": 0.571689,
        "manhattan_recall": 0.917889,
        "manhattan_ap": 0.672964,
        "euclidean_accuracy": 0.642491,
        "euclidean_accuracy_threshold": 0.489373,
        "euclidean_f1": 0.703911,
        "euclidean_f1_threshold": 0.571498,
        "euclidean_precision": 0.568592,
        "euclidean_recall": 0.923754,
        "euclidean_ap": 0.673372,
        "dot_accuracy": 0.642491,
        "dot_accuracy_threshold": 0.880257,
        "dot_f1": 0.703911,
        "dot_f1_threshold": 0.836695,
        "dot_precision": 0.568592,
        "dot_recall": 0.923754,
        "dot_ap": 0.673373,
        "max_accuracy": 0.642491,
        "max_f1": 0.704558,
        "max_precision": 0.571689,
        "max_recall": 0.923754,
        "max_ap": 0.673373,
        "main_score": 0.673373,
        "hf_subset": "ar",
        "languages": [
          "ara-Arab"
        ]
      },
      {
        "similarity_accuracy": 0.660073,
        "similarity_accuracy_threshold": 0.874732,
        "similarity_f1": 0.694652,
        "similarity_f1_threshold": 0.849247,
        "similarity_precision": 0.571429,
        "similarity_recall": 0.88563,
        "similarity_ap": 0.68653,
        "cosine_accuracy": 0.660073,
        "cosine_accuracy_threshold": 0.874732,
        "cosine_f1": 0.694652,
        "cosine_f1_threshold": 0.849247,
        "cosine_precision": 0.571429,
        "cosine_recall": 0.88563,
        "cosine_ap": 0.68653,
        "manhattan_accuracy": 0.659341,
        "manhattan_accuracy_threshold": 10.66827,
        "manhattan_f1": 0.693714,
        "manhattan_f1_threshold": 12.139343,
        "manhattan_precision": 0.568352,
        "manhattan_recall": 0.890029,
        "manhattan_ap": 0.683797,
        "euclidean_accuracy": 0.660073,
        "euclidean_accuracy_threshold": 0.500535,
        "euclidean_f1": 0.694652,
        "euclidean_f1_threshold": 0.549095,
        "euclidean_precision": 0.571429,
        "euclidean_recall": 0.88563,
        "euclidean_ap": 0.68653,
        "dot_accuracy": 0.660073,
        "dot_accuracy_threshold": 0.874732,
        "dot_f1": 0.694652,
        "dot_f1_threshold": 0.849247,
        "dot_precision": 0.571429,
        "dot_recall": 0.88563,
        "dot_ap": 0.68653,
        "max_accuracy": 0.660073,
        "max_f1": 0.694652,
        "max_precision": 0.571429,
        "max_recall": 0.890029,
        "max_ap": 0.68653,
        "main_score": 0.68653,
        "hf_subset": "bg",
        "languages": [
          "bul-Cyrl"
        ]
      },
      {
        "similarity_accuracy": 0.666667,
        "similarity_accuracy_threshold": 0.863539,
        "similarity_f1": 0.709281,
        "similarity_f1_threshold": 0.852655,
        "similarity_precision": 0.610582,
        "similarity_recall": 0.846041,
        "similarity_ap": 0.6911,
        "cosine_accuracy": 0.666667,
        "cosine_accuracy_threshold": 0.863539,
        "cosine_f1": 0.709281,
        "cosine_f1_threshold": 0.852655,
        "cosine_precision": 0.610582,
        "cosine_recall": 0.846041,
        "cosine_ap": 0.6911,
        "manhattan_accuracy": 0.664469,
        "manhattan_accuracy_threshold": 11.121737,
        "manhattan_f1": 0.710074,
        "manhattan_f1_threshold": 11.906858,
        "manhattan_precision": 0.610994,
        "manhattan_recall": 0.847507,
        "manhattan_ap": 0.68934,
        "euclidean_accuracy": 0.666667,
        "euclidean_accuracy_threshold": 0.52242,
        "euclidean_f1": 0.709281,
        "euclidean_f1_threshold": 0.542853,
        "euclidean_precision": 0.610582,
        "euclidean_recall": 0.846041,
        "euclidean_ap": 0.6911,
        "dot_accuracy": 0.666667,
        "dot_accuracy_threshold": 0.863539,
        "dot_f1": 0.709281,
        "dot_f1_threshold": 0.852655,
        "dot_precision": 0.610582,
        "dot_recall": 0.846041,
        "dot_ap": 0.6911,
        "max_accuracy": 0.666667,
        "max_f1": 0.710074,
        "max_precision": 0.610994,
        "max_recall": 0.847507,
        "max_ap": 0.6911,
        "main_score": 0.6911,
        "hf_subset": "de",
        "languages": [
          "deu-Latn"
        ]
      },
      {
        "similarity_accuracy": 0.657143,
        "similarity_accuracy_threshold": 0.8655,
        "similarity_f1": 0.699584,
        "similarity_f1_threshold": 0.851949,
        "similarity_precision": 0.588589,
        "similarity_recall": 0.86217,
        "similarity_ap": 0.705785,
        "cosine_accuracy": 0.657143,
        "cosine_accuracy_threshold": 0.8655,
        "cosine_f1": 0.699584,
        "cosine_f1_threshold": 0.851949,
        "cosine_precision": 0.588589,
        "cosine_recall": 0.86217,
        "cosine_ap": 0.705785,
        "manhattan_accuracy": 0.657875,
        "manhattan_accuracy_threshold": 11.000895,
        "manhattan_f1": 0.701068,
        "manhattan_f1_threshold": 12.025171,
        "manhattan_precision": 0.588645,
        "manhattan_recall": 0.866569,
        "manhattan_ap": 0.704236,
        "euclidean_accuracy": 0.657143,
        "euclidean_accuracy_threshold": 0.518653,
        "euclidean_f1": 0.699584,
        "euclidean_f1_threshold": 0.544153,
        "euclidean_precision": 0.588589,
        "euclidean_recall": 0.86217,
        "euclidean_ap": 0.705785,
        "dot_accuracy": 0.657143,
        "dot_accuracy_threshold": 0.8655,
        "dot_f1": 0.699584,
        "dot_f1_threshold": 0.851949,
        "dot_precision": 0.588589,
        "dot_recall": 0.86217,
        "dot_ap": 0.705783,
        "max_accuracy": 0.657875,
        "max_f1": 0.701068,
        "max_precision": 0.588645,
        "max_recall": 0.866569,
        "max_ap": 0.705785,
        "main_score": 0.705785,
        "hf_subset": "el",
        "languages": [
          "ell-Grek"
        ]
      },
      {
        "similarity_accuracy": 0.748718,
        "similarity_accuracy_threshold": 0.862646,
        "similarity_f1": 0.766623,
        "similarity_f1_threshold": 0.851286,
        "similarity_precision": 0.690141,
        "similarity_recall": 0.86217,
        "similarity_ap": 0.786164,
        "cosine_accuracy": 0.748718,
        "cosine_accuracy_threshold": 0.862646,
        "cosine_f1": 0.766623,
        "cosine_f1_threshold": 0.851286,
        "cosine_precision": 0.690141,
        "cosine_recall": 0.86217,
        "cosine_ap": 0.786164,
        "manhattan_accuracy": 0.750183,
        "manhattan_accuracy_threshold": 11.376371,
        "manhattan_f1": 0.763291,
        "manhattan_f1_threshold": 12.172159,
        "manhattan_precision": 0.671492,
        "manhattan_recall": 0.884164,
        "manhattan_ap": 0.784402,
        "euclidean_accuracy": 0.748718,
        "euclidean_accuracy_threshold": 0.524126,
        "euclidean_f1": 0.766623,
        "euclidean_f1_threshold": 0.54537,
        "euclidean_precision": 0.690141,
        "euclidean_recall": 0.86217,
        "euclidean_ap": 0.786164,
        "dot_accuracy": 0.748718,
        "dot_accuracy_threshold": 0.862646,
        "dot_f1": 0.766623,
        "dot_f1_threshold": 0.851286,
        "dot_precision": 0.690141,
        "dot_recall": 0.86217,
        "dot_ap": 0.786164,
        "max_accuracy": 0.750183,
        "max_f1": 0.766623,
        "max_precision": 0.690141,
        "max_recall": 0.884164,
        "max_ap": 0.786164,
        "main_score": 0.786164,
        "hf_subset": "en",
        "languages": [
          "eng-Latn"
        ]
      },
      {
        "similarity_accuracy": 0.679121,
        "similarity_accuracy_threshold": 0.872582,
        "similarity_f1": 0.710889,
        "similarity_f1_threshold": 0.856399,
        "similarity_precision": 0.620087,
        "similarity_recall": 0.832845,
        "similarity_ap": 0.718872,
        "cosine_accuracy": 0.679121,
        "cosine_accuracy_threshold": 0.872582,
        "cosine_f1": 0.710889,
        "cosine_f1_threshold": 0.856399,
        "cosine_precision": 0.620087,
        "cosine_recall": 0.832845,
        "cosine_ap": 0.718872,
        "manhattan_accuracy": 0.673993,
        "manhattan_accuracy_threshold": 11.212557,
        "manhattan_f1": 0.710448,
        "manhattan_f1_threshold": 12.06778,
        "manhattan_precision": 0.599194,
        "manhattan_recall": 0.872434,
        "manhattan_ap": 0.716489,
        "euclidean_accuracy": 0.679121,
        "euclidean_accuracy_threshold": 0.504812,
        "euclidean_f1": 0.710889,
        "euclidean_f1_threshold": 0.535913,
        "euclidean_precision": 0.620087,
        "euclidean_recall": 0.832845,
        "euclidean_ap": 0.718872,
        "dot_accuracy": 0.679121,
        "dot_accuracy_threshold": 0.872582,
        "dot_f1": 0.710889,
        "dot_f1_threshold": 0.856399,
        "dot_precision": 0.620087,
        "dot_recall": 0.832845,
        "dot_ap": 0.718872,
        "max_accuracy": 0.679121,
        "max_f1": 0.710889,
        "max_precision": 0.620087,
        "max_recall": 0.872434,
        "max_ap": 0.718872,
        "main_score": 0.718872,
        "hf_subset": "es",
        "languages": [
          "spa-Latn"
        ]
      },
      {
        "similarity_accuracy": 0.681319,
        "similarity_accuracy_threshold": 0.870775,
        "similarity_f1": 0.718009,
        "similarity_f1_threshold": 0.846467,
        "similarity_precision": 0.602386,
        "similarity_recall": 0.888563,
        "similarity_ap": 0.732762,
        "cosine_accuracy": 0.681319,
        "cosine_accuracy_threshold": 0.870775,
        "cosine_f1": 0.718009,
        "cosine_f1_threshold": 0.846467,
        "cosine_precision": 0.602386,
        "cosine_recall": 0.888563,
        "cosine_ap": 0.732762,
        "manhattan_accuracy": 0.677656,
        "manhattan_accuracy_threshold": 11.241543,
        "manhattan_f1": 0.717799,
        "manhattan_f1_threshold": 12.25897,
        "manhattan_precision": 0.597466,
        "manhattan_recall": 0.898827,
        "manhattan_ap": 0.73225,
        "euclidean_accuracy": 0.681319,
        "euclidean_accuracy_threshold": 0.50838,
        "euclidean_f1": 0.718009,
        "euclidean_f1_threshold": 0.554135,
        "euclidean_precision": 0.602386,
        "euclidean_recall": 0.888563,
        "euclidean_ap": 0.732762,
        "dot_accuracy": 0.681319,
        "dot_accuracy_threshold": 0.870775,
        "dot_f1": 0.718009,
        "dot_f1_threshold": 0.846467,
        "dot_precision": 0.602386,
        "dot_recall": 0.888563,
        "dot_ap": 0.732762,
        "max_accuracy": 0.681319,
        "max_f1": 0.718009,
        "max_precision": 0.602386,
        "max_recall": 0.898827,
        "max_ap": 0.732762,
        "main_score": 0.732762,
        "hf_subset": "fr",
        "languages": [
          "fra-Latn"
        ]
      },
      {
        "similarity_accuracy": 0.664469,
        "similarity_accuracy_threshold": 0.846682,
        "similarity_f1": 0.693878,
        "similarity_f1_threshold": 0.803684,
        "similarity_precision": 0.565619,
        "similarity_recall": 0.897361,
        "similarity_ap": 0.714986,
        "cosine_accuracy": 0.664469,
        "cosine_accuracy_threshold": 0.846682,
        "cosine_f1": 0.693878,
        "cosine_f1_threshold": 0.803684,
        "cosine_precision": 0.565619,
        "cosine_recall": 0.897361,
        "cosine_ap": 0.714986,
        "manhattan_accuracy": 0.662271,
        "manhattan_accuracy_threshold": 11.969074,
        "manhattan_f1": 0.692395,
        "manhattan_f1_threshold": 13.812998,
        "manhattan_precision": 0.564815,
        "manhattan_recall": 0.894428,
        "manhattan_ap": 0.716396,
        "euclidean_accuracy": 0.664469,
        "euclidean_accuracy_threshold": 0.553747,
        "euclidean_f1": 0.693878,
        "euclidean_f1_threshold": 0.626603,
        "euclidean_precision": 0.565619,
        "euclidean_recall": 0.897361,
        "euclidean_ap": 0.714986,
        "dot_accuracy": 0.664469,
        "dot_accuracy_threshold": 0.846682,
        "dot_f1": 0.693878,
        "dot_f1_threshold": 0.803684,
        "dot_precision": 0.565619,
        "dot_recall": 0.897361,
        "dot_ap": 0.714987,
        "max_accuracy": 0.664469,
        "max_f1": 0.693878,
        "max_precision": 0.565619,
        "max_recall": 0.897361,
        "max_ap": 0.716396,
        "main_score": 0.716396,
        "hf_subset": "hi",
        "languages": [
          "hin-Deva"
        ]
      },
      {
        "similarity_accuracy": 0.680586,
        "similarity_accuracy_threshold": 0.866661,
        "similarity_f1": 0.716867,
        "similarity_f1_threshold": 0.834368,
        "similarity_precision": 0.608384,
        "similarity_recall": 0.872434,
        "similarity_ap": 0.741265,
        "cosine_accuracy": 0.680586,
        "cosine_accuracy_threshold": 0.866661,
        "cosine_f1": 0.716867,
        "cosine_f1_threshold": 0.834368,
        "cosine_precision": 0.608384,
        "cosine_recall": 0.872434,
        "cosine_ap": 0.741265,
        "manhattan_accuracy": 0.681319,
        "manhattan_accuracy_threshold": 11.504902,
        "manhattan_f1": 0.71891,
        "manhattan_f1_threshold": 13.041861,
        "manhattan_precision": 0.586654,
        "manhattan_recall": 0.928152,
        "manhattan_ap": 0.74086,
        "euclidean_accuracy": 0.680586,
        "euclidean_accuracy_threshold": 0.516409,
        "euclidean_f1": 0.716867,
        "euclidean_f1_threshold": 0.575554,
        "euclidean_precision": 0.608384,
        "euclidean_recall": 0.872434,
        "euclidean_ap": 0.741265,
        "dot_accuracy": 0.680586,
        "dot_accuracy_threshold": 0.866661,
        "dot_f1": 0.716867,
        "dot_f1_threshold": 0.834369,
        "dot_precision": 0.608384,
        "dot_recall": 0.872434,
        "dot_ap": 0.741265,
        "max_accuracy": 0.681319,
        "max_f1": 0.71891,
        "max_precision": 0.608384,
        "max_recall": 0.928152,
        "max_ap": 0.741265,
        "main_score": 0.741265,
        "hf_subset": "ru",
        "languages": [
          "rus-Cyrl"
        ]
      },
      {
        "similarity_accuracy": 0.635897,
        "similarity_accuracy_threshold": 0.8397,
        "similarity_f1": 0.698851,
        "similarity_f1_threshold": 0.819044,
        "similarity_precision": 0.574669,
        "similarity_recall": 0.891496,
        "similarity_ap": 0.68051,
        "cosine_accuracy": 0.635897,
        "cosine_accuracy_threshold": 0.8397,
        "cosine_f1": 0.698851,
        "cosine_f1_threshold": 0.819044,
        "cosine_precision": 0.574669,
        "cosine_recall": 0.891496,
        "cosine_ap": 0.68051,
        "manhattan_accuracy": 0.63956,
        "manhattan_accuracy_threshold": 12.300909,
        "manhattan_f1": 0.694994,
        "manhattan_f1_threshold": 13.175343,
        "manhattan_precision": 0.576255,
        "manhattan_recall": 0.875367,
        "manhattan_ap": 0.679289,
        "euclidean_accuracy": 0.635897,
        "euclidean_accuracy_threshold": 0.566216,
        "euclidean_f1": 0.698851,
        "euclidean_f1_threshold": 0.601591,
        "euclidean_precision": 0.574669,
        "euclidean_recall": 0.891496,
        "euclidean_ap": 0.68051,
        "dot_accuracy": 0.635897,
        "dot_accuracy_threshold": 0.8397,
        "dot_f1": 0.698851,
        "dot_f1_threshold": 0.819044,
        "dot_precision": 0.574669,
        "dot_recall": 0.891496,
        "dot_ap": 0.68051,
        "max_accuracy": 0.63956,
        "max_f1": 0.698851,
        "max_precision": 0.576255,
        "max_recall": 0.891496,
        "max_ap": 0.68051,
        "main_score": 0.68051,
        "hf_subset": "sw",
        "languages": [
          "swa-Latn"
        ]
      },
      {
        "similarity_accuracy": 0.654945,
        "similarity_accuracy_threshold": 0.867538,
        "similarity_f1": 0.700961,
        "similarity_f1_threshold": 0.828861,
        "similarity_precision": 0.570377,
        "similarity_recall": 0.909091,
        "similarity_ap": 0.697355,
        "cosine_accuracy": 0.654945,
        "cosine_accuracy_threshold": 0.867538,
        "cosine_f1": 0.700961,
        "cosine_f1_threshold": 0.828861,
        "cosine_precision": 0.570377,
        "cosine_recall": 0.909091,
        "cosine_ap": 0.697355,
        "manhattan_accuracy": 0.655678,
        "manhattan_accuracy_threshold": 11.326759,
        "manhattan_f1": 0.699941,
        "manhattan_f1_threshold": 12.637931,
        "manhattan_precision": 0.583741,
        "manhattan_recall": 0.8739,
        "manhattan_ap": 0.696649,
        "euclidean_accuracy": 0.654945,
        "euclidean_accuracy_threshold": 0.514709,
        "euclidean_f1": 0.700961,
        "euclidean_f1_threshold": 0.585046,
        "euclidean_precision": 0.570377,
        "euclidean_recall": 0.909091,
        "euclidean_ap": 0.697355,
        "dot_accuracy": 0.654945,
        "dot_accuracy_threshold": 0.867538,
        "dot_f1": 0.700961,
        "dot_f1_threshold": 0.828861,
        "dot_precision": 0.570377,
        "dot_recall": 0.909091,
        "dot_ap": 0.69736,
        "max_accuracy": 0.655678,
        "max_f1": 0.700961,
        "max_precision": 0.583741,
        "max_recall": 0.909091,
        "max_ap": 0.69736,
        "main_score": 0.69736,
        "hf_subset": "th",
        "languages": [
          "tha-Thai"
        ]
      },
      {
        "similarity_accuracy": 0.651282,
        "similarity_accuracy_threshold": 0.855274,
        "similarity_f1": 0.701373,
        "similarity_f1_threshold": 0.835101,
        "similarity_precision": 0.575047,
        "similarity_recall": 0.898827,
        "similarity_ap": 0.688172,
        "cosine_accuracy": 0.651282,
        "cosine_accuracy_threshold": 0.855274,
        "cosine_f1": 0.701373,
        "cosine_f1_threshold": 0.835101,
        "cosine_precision": 0.575047,
        "cosine_recall": 0.898827,
        "cosine_ap": 0.688172,
        "manhattan_accuracy": 0.647619,
        "manhattan_accuracy_threshold": 11.864082,
        "manhattan_f1": 0.698795,
        "manhattan_f1_threshold": 12.622618,
        "manhattan_precision": 0.573987,
        "manhattan_recall": 0.892962,
        "manhattan_ap": 0.686125,
        "euclidean_accuracy": 0.651282,
        "euclidean_accuracy_threshold": 0.538007,
        "euclidean_f1": 0.701373,
        "euclidean_f1_threshold": 0.574281,
        "euclidean_precision": 0.575047,
        "euclidean_recall": 0.898827,
        "euclidean_ap": 0.688172,
        "dot_accuracy": 0.651282,
        "dot_accuracy_threshold": 0.855274,
        "dot_f1": 0.701373,
        "dot_f1_threshold": 0.835101,
        "dot_precision": 0.575047,
        "dot_recall": 0.898827,
        "dot_ap": 0.688172,
        "max_accuracy": 0.651282,
        "max_f1": 0.701373,
        "max_precision": 0.575047,
        "max_recall": 0.898827,
        "max_ap": 0.688172,
        "main_score": 0.688172,
        "hf_subset": "tr",
        "languages": [
          "tur-Latn"
        ]
      },
      {
        "similarity_accuracy": 0.669597,
        "similarity_accuracy_threshold": 0.879159,
        "similarity_f1": 0.707622,
        "similarity_f1_threshold": 0.847585,
        "similarity_precision": 0.578067,
        "similarity_recall": 0.912023,
        "similarity_ap": 0.709795,
        "cosine_accuracy": 0.669597,
        "cosine_accuracy_threshold": 0.879159,
        "cosine_f1": 0.707622,
        "cosine_f1_threshold": 0.847585,
        "cosine_precision": 0.578067,
        "cosine_recall": 0.912023,
        "cosine_ap": 0.709795,
        "manhattan_accuracy": 0.668864,
        "manhattan_accuracy_threshold": 10.538826,
        "manhattan_f1": 0.707537,
        "manhattan_f1_threshold": 12.239641,
        "manhattan_precision": 0.573905,
        "manhattan_recall": 0.922287,
        "manhattan_ap": 0.708811,
        "euclidean_accuracy": 0.669597,
        "euclidean_accuracy_threshold": 0.491612,
        "euclidean_f1": 0.707622,
        "euclidean_f1_threshold": 0.552115,
        "euclidean_precision": 0.578067,
        "euclidean_recall": 0.912023,
        "euclidean_ap": 0.709795,
        "dot_accuracy": 0.669597,
        "dot_accuracy_threshold": 0.879159,
        "dot_f1": 0.707622,
        "dot_f1_threshold": 0.847585,
        "dot_precision": 0.578067,
        "dot_recall": 0.912023,
        "dot_ap": 0.709795,
        "max_accuracy": 0.669597,
        "max_f1": 0.707622,
        "max_precision": 0.578067,
        "max_recall": 0.922287,
        "max_ap": 0.709795,
        "main_score": 0.709795,
        "hf_subset": "vi",
        "languages": [
          "vie-Latn"
        ]
      },
      {
        "similarity_accuracy": 0.671062,
        "similarity_accuracy_threshold": 0.885382,
        "similarity_f1": 0.709069,
        "similarity_f1_threshold": 0.866005,
        "similarity_precision": 0.59252,
        "similarity_recall": 0.882698,
        "similarity_ap": 0.69729,
        "cosine_accuracy": 0.671062,
        "cosine_accuracy_threshold": 0.885382,
        "cosine_f1": 0.709069,
        "cosine_f1_threshold": 0.866005,
        "cosine_precision": 0.59252,
        "cosine_recall": 0.882698,
        "cosine_ap": 0.69729,
        "manhattan_accuracy": 0.663736,
        "manhattan_accuracy_threshold": 10.582314,
        "manhattan_f1": 0.70561,
        "manhattan_f1_threshold": 11.513924,
        "manhattan_precision": 0.582617,
        "manhattan_recall": 0.894428,
        "manhattan_ap": 0.696805,
        "euclidean_accuracy": 0.671062,
        "euclidean_accuracy_threshold": 0.478785,
        "euclidean_f1": 0.709069,
        "euclidean_f1_threshold": 0.517677,
        "euclidean_precision": 0.59252,
        "euclidean_recall": 0.882698,
        "euclidean_ap": 0.69729,
        "dot_accuracy": 0.671062,
        "dot_accuracy_threshold": 0.885382,
        "dot_f1": 0.709069,
        "dot_f1_threshold": 0.866005,
        "dot_precision": 0.59252,
        "dot_recall": 0.882698,
        "dot_ap": 0.697289,
        "max_accuracy": 0.671062,
        "max_f1": 0.709069,
        "max_precision": 0.59252,
        "max_recall": 0.894428,
        "max_ap": 0.69729,
        "main_score": 0.69729,
        "hf_subset": "zh",
        "languages": [
          "zho-Hans"
        ]
      }
    ],
    "validation": [
      {
        "similarity_accuracy": 0.668864,
        "similarity_accuracy_threshold": 0.87866,
        "similarity_f1": 0.697484,
        "similarity_f1_threshold": 0.842198,
        "similarity_precision": 0.580331,
        "similarity_recall": 0.8739,
        "similarity_ap": 0.722431,
        "cosine_accuracy": 0.668864,
        "cosine_accuracy_threshold": 0.87866,
        "cosine_f1": 0.697484,
        "cosine_f1_threshold": 0.842198,
        "cosine_precision": 0.580331,
        "cosine_recall": 0.8739,
        "cosine_ap": 0.722431,
        "manhattan_accuracy": 0.666667,
        "manhattan_accuracy_threshold": 11.17001,
        "manhattan_f1": 0.698281,
        "manhattan_f1_threshold": 12.301565,
        "manhattan_precision": 0.58607,
        "manhattan_recall": 0.863636,
        "manhattan_ap": 0.720868,
        "euclidean_accuracy": 0.668864,
        "euclidean_accuracy_threshold": 0.492626,
        "euclidean_f1": 0.697484,
        "euclidean_f1_threshold": 0.561787,
        "euclidean_precision": 0.580331,
        "euclidean_recall": 0.8739,
        "euclidean_ap": 0.722433,
        "dot_accuracy": 0.668864,
        "dot_accuracy_threshold": 0.87866,
        "dot_f1": 0.697484,
        "dot_f1_threshold": 0.842198,
        "dot_precision": 0.580331,
        "dot_recall": 0.8739,
        "dot_ap": 0.722431,
        "max_accuracy": 0.668864,
        "max_f1": 0.698281,
        "max_precision": 0.58607,
        "max_recall": 0.8739,
        "max_ap": 0.722433,
        "main_score": 0.722433,
        "hf_subset": "ar",
        "languages": [
          "ara-Arab"
        ]
      },
      {
        "similarity_accuracy": 0.67326,
        "similarity_accuracy_threshold": 0.870806,
        "similarity_f1": 0.698287,
        "similarity_f1_threshold": 0.866125,
        "similarity_precision": 0.633971,
        "similarity_recall": 0.777126,
        "similarity_ap": 0.71867,
        "cosine_accuracy": 0.67326,
        "cosine_accuracy_threshold": 0.870806,
        "cosine_f1": 0.698287,
        "cosine_f1_threshold": 0.866125,
        "cosine_precision": 0.633971,
        "cosine_recall": 0.777126,
        "cosine_ap": 0.71867,
        "manhattan_accuracy": 0.671795,
        "manhattan_accuracy_threshold": 11.285897,
        "manhattan_f1": 0.699418,
        "manhattan_f1_threshold": 11.457872,
        "manhattan_precision": 0.625434,
        "manhattan_recall": 0.793255,
        "manhattan_ap": 0.717317,
        "euclidean_accuracy": 0.67326,
        "euclidean_accuracy_threshold": 0.508319,
        "euclidean_f1": 0.698287,
        "euclidean_f1_threshold": 0.517446,
        "euclidean_precision": 0.633971,
        "euclidean_recall": 0.777126,
        "euclidean_ap": 0.718673,
        "dot_accuracy": 0.67326,
        "dot_accuracy_threshold": 0.870806,
        "dot_f1": 0.698287,
        "dot_f1_threshold": 0.866125,
        "dot_precision": 0.633971,
        "dot_recall": 0.777126,
        "dot_ap": 0.718669,
        "max_accuracy": 0.67326,
        "max_f1": 0.699418,
        "max_precision": 0.633971,
        "max_recall": 0.793255,
        "max_ap": 0.718673,
        "main_score": 0.718673,
        "hf_subset": "bg",
        "languages": [
          "bul-Cyrl"
        ]
      },
      {
        "similarity_accuracy": 0.676923,
        "similarity_accuracy_threshold": 0.873801,
        "similarity_f1": 0.701282,
        "similarity_f1_threshold": 0.859036,
        "similarity_precision": 0.623007,
        "similarity_recall": 0.802053,
        "similarity_ap": 0.71615,
        "cosine_accuracy": 0.676923,
        "cosine_accuracy_threshold": 0.873801,
        "cosine_f1": 0.701282,
        "cosine_f1_threshold": 0.859036,
        "cosine_precision": 0.623007,
        "cosine_recall": 0.802053,
        "cosine_ap": 0.71615,
        "manhattan_accuracy": 0.676923,
        "manhattan_accuracy_threshold": 11.016375,
        "manhattan_f1": 0.700243,
        "manhattan_f1_threshold": 12.022909,
        "manhattan_precision": 0.597308,
        "manhattan_recall": 0.846041,
        "manhattan_ap": 0.71628,
        "euclidean_accuracy": 0.676923,
        "euclidean_accuracy_threshold": 0.502393,
        "euclidean_f1": 0.701282,
        "euclidean_f1_threshold": 0.53097,
        "euclidean_precision": 0.623007,
        "euclidean_recall": 0.802053,
        "euclidean_ap": 0.71615,
        "dot_accuracy": 0.676923,
        "dot_accuracy_threshold": 0.873801,
        "dot_f1": 0.701282,
        "dot_f1_threshold": 0.859036,
        "dot_precision": 0.623007,
        "dot_recall": 0.802053,
        "dot_ap": 0.71615,
        "max_accuracy": 0.676923,
        "max_f1": 0.701282,
        "max_precision": 0.623007,
        "max_recall": 0.846041,
        "max_ap": 0.71628,
        "main_score": 0.71628,
        "hf_subset": "de",
        "languages": [
          "deu-Latn"
        ]
      },
      {
        "similarity_accuracy": 0.659341,
        "similarity_accuracy_threshold": 0.877487,
        "similarity_f1": 0.69482,
        "similarity_f1_threshold": 0.841559,
        "similarity_precision": 0.563985,
        "similarity_recall": 0.904692,
        "similarity_ap": 0.7173,
        "cosine_accuracy": 0.659341,
        "cosine_accuracy_threshold": 0.877487,
        "cosine_f1": 0.69482,
        "cosine_f1_threshold": 0.841559,
        "cosine_precision": 0.563985,
        "cosine_recall": 0.904692,
        "cosine_ap": 0.7173,
        "manhattan_accuracy": 0.660806,
        "manhattan_accuracy_threshold": 10.743212,
        "manhattan_f1": 0.695169,
        "manhattan_f1_threshold": 12.494445,
        "manhattan_precision": 0.559428,
        "manhattan_recall": 0.917889,
        "manhattan_ap": 0.715603,
        "euclidean_accuracy": 0.659341,
        "euclidean_accuracy_threshold": 0.495,
        "euclidean_f1": 0.69482,
        "euclidean_f1_threshold": 0.562922,
        "euclidean_precision": 0.563985,
        "euclidean_recall": 0.904692,
        "euclidean_ap": 0.7173,
        "dot_accuracy": 0.659341,
        "dot_accuracy_threshold": 0.877487,
        "dot_f1": 0.69482,
        "dot_f1_threshold": 0.841559,
        "dot_precision": 0.563985,
        "dot_recall": 0.904692,
        "dot_ap": 0.7173,
        "max_accuracy": 0.660806,
        "max_f1": 0.695169,
        "max_precision": 0.563985,
        "max_recall": 0.917889,
        "max_ap": 0.7173,
        "main_score": 0.7173,
        "hf_subset": "el",
        "languages": [
          "ell-Grek"
        ]
      },
      {
        "similarity_accuracy": 0.745788,
        "similarity_accuracy_threshold": 0.861003,
        "similarity_f1": 0.764281,
        "similarity_f1_threshold": 0.850538,
        "similarity_precision": 0.692033,
        "similarity_recall": 0.853372,
        "similarity_ap": 0.813746,
        "cosine_accuracy": 0.745788,
        "cosine_accuracy_threshold": 0.861003,
        "cosine_f1": 0.764281,
        "cosine_f1_threshold": 0.850538,
        "cosine_precision": 0.692033,
        "cosine_recall": 0.853372,
        "cosine_ap": 0.813746,
        "manhattan_accuracy": 0.741392,
        "manhattan_accuracy_threshold": 11.729996,
        "manhattan_f1": 0.763683,
        "manhattan_f1_threshold": 12.182473,
        "manhattan_precision": 0.680827,
        "manhattan_recall": 0.869501,
        "manhattan_ap": 0.812225,
        "euclidean_accuracy": 0.745788,
        "euclidean_accuracy_threshold": 0.527251,
        "euclidean_f1": 0.764281,
        "euclidean_f1_threshold": 0.54674,
        "euclidean_precision": 0.692033,
        "euclidean_recall": 0.853372,
        "euclidean_ap": 0.813746,
        "dot_accuracy": 0.745788,
        "dot_accuracy_threshold": 0.861003,
        "dot_f1": 0.764281,
        "dot_f1_threshold": 0.850538,
        "dot_precision": 0.692033,
        "dot_recall": 0.853372,
        "dot_ap": 0.813746,
        "max_accuracy": 0.745788,
        "max_f1": 0.764281,
        "max_precision": 0.692033,
        "max_recall": 0.869501,
        "max_ap": 0.813746,
        "main_score": 0.813746,
        "hf_subset": "en",
        "languages": [
          "eng-Latn"
        ]
      },
      {
        "similarity_accuracy": 0.694505,
        "similarity_accuracy_threshold": 0.870299,
        "similarity_f1": 0.715889,
        "similarity_f1_threshold": 0.84453,
        "similarity_precision": 0.599407,
        "similarity_recall": 0.888563,
        "similarity_ap": 0.734547,
        "cosine_accuracy": 0.694505,
        "cosine_accuracy_threshold": 0.870299,
        "cosine_f1": 0.715889,
        "cosine_f1_threshold": 0.84453,
        "cosine_precision": 0.599407,
        "cosine_recall": 0.888563,
        "cosine_ap": 0.734547,
        "manhattan_accuracy": 0.69304,
        "manhattan_accuracy_threshold": 11.231012,
        "manhattan_f1": 0.713864,
        "manhattan_f1_threshold": 12.282172,
        "manhattan_precision": 0.597236,
        "manhattan_recall": 0.887097,
        "manhattan_ap": 0.732255,
        "euclidean_accuracy": 0.694505,
        "euclidean_accuracy_threshold": 0.509315,
        "euclidean_f1": 0.715889,
        "euclidean_f1_threshold": 0.55762,
        "euclidean_precision": 0.599407,
        "euclidean_recall": 0.888563,
        "euclidean_ap": 0.734547,
        "dot_accuracy": 0.694505,
        "dot_accuracy_threshold": 0.870299,
        "dot_f1": 0.715889,
        "dot_f1_threshold": 0.84453,
        "dot_precision": 0.599407,
        "dot_recall": 0.888563,
        "dot_ap": 0.734547,
        "max_accuracy": 0.694505,
        "max_f1": 0.715889,
        "max_precision": 0.599407,
        "max_recall": 0.888563,
        "max_ap": 0.734547,
        "main_score": 0.734547,
        "hf_subset": "es",
        "languages": [
          "spa-Latn"
        ]
      },
      {
        "similarity_accuracy": 0.689377,
        "similarity_accuracy_threshold": 0.862817,
        "similarity_f1": 0.729713,
        "similarity_f1_threshold": 0.850017,
        "similarity_precision": 0.624869,
        "similarity_recall": 0.876833,
        "similarity_ap": 0.749256,
        "cosine_accuracy": 0.689377,
        "cosine_accuracy_threshold": 0.862817,
        "cosine_f1": 0.729713,
        "cosine_f1_threshold": 0.850017,
        "cosine_precision": 0.624869,
        "cosine_recall": 0.876833,
        "cosine_ap": 0.749256,
        "manhattan_accuracy": 0.691575,
        "manhattan_accuracy_threshold": 11.480341,
        "manhattan_f1": 0.725153,
        "manhattan_f1_threshold": 12.026807,
        "manhattan_precision": 0.623418,
        "manhattan_recall": 0.866569,
        "manhattan_ap": 0.748574,
        "euclidean_accuracy": 0.689377,
        "euclidean_accuracy_threshold": 0.523799,
        "euclidean_f1": 0.729713,
        "euclidean_f1_threshold": 0.547692,
        "euclidean_precision": 0.624869,
        "euclidean_recall": 0.876833,
        "euclidean_ap": 0.749254,
        "dot_accuracy": 0.689377,
        "dot_accuracy_threshold": 0.862817,
        "dot_f1": 0.729713,
        "dot_f1_threshold": 0.850017,
        "dot_precision": 0.624869,
        "dot_recall": 0.876833,
        "dot_ap": 0.749255,
        "max_accuracy": 0.691575,
        "max_f1": 0.729713,
        "max_precision": 0.624869,
        "max_recall": 0.876833,
        "max_ap": 0.749256,
        "main_score": 0.749256,
        "hf_subset": "fr",
        "languages": [
          "fra-Latn"
        ]
      },
      {
        "similarity_accuracy": 0.668864,
        "similarity_accuracy_threshold": 0.847793,
        "similarity_f1": 0.691589,
        "similarity_f1_threshold": 0.793034,
        "similarity_precision": 0.55321,
        "similarity_recall": 0.922287,
        "similarity_ap": 0.732231,
        "cosine_accuracy": 0.668864,
        "cosine_accuracy_threshold": 0.847793,
        "cosine_f1": 0.691589,
        "cosine_f1_threshold": 0.793034,
        "cosine_precision": 0.55321,
        "cosine_recall": 0.922287,
        "cosine_ap": 0.732231,
        "manhattan_accuracy": 0.668132,
        "manhattan_accuracy_threshold": 12.620877,
        "manhattan_f1": 0.691094,
        "manhattan_f1_threshold": 13.962765,
        "manhattan_precision": 0.561355,
        "manhattan_recall": 0.898827,
        "manhattan_ap": 0.730207,
        "euclidean_accuracy": 0.668864,
        "euclidean_accuracy_threshold": 0.551736,
        "euclidean_f1": 0.691589,
        "euclidean_f1_threshold": 0.643376,
        "euclidean_precision": 0.55321,
        "euclidean_recall": 0.922287,
        "euclidean_ap": 0.732231,
        "dot_accuracy": 0.668864,
        "dot_accuracy_threshold": 0.847793,
        "dot_f1": 0.691589,
        "dot_f1_threshold": 0.793034,
        "dot_precision": 0.55321,
        "dot_recall": 0.922287,
        "dot_ap": 0.732231,
        "max_accuracy": 0.668864,
        "max_f1": 0.691589,
        "max_precision": 0.561355,
        "max_recall": 0.922287,
        "max_ap": 0.732231,
        "main_score": 0.732231,
        "hf_subset": "hi",
        "languages": [
          "hin-Deva"
        ]
      },
      {
        "similarity_accuracy": 0.677656,
        "similarity_accuracy_threshold": 0.848983,
        "similarity_f1": 0.7125,
        "similarity_f1_threshold": 0.838166,
        "similarity_precision": 0.620915,
        "similarity_recall": 0.835777,
        "similarity_ap": 0.750355,
        "cosine_accuracy": 0.677656,
        "cosine_accuracy_threshold": 0.848983,
        "cosine_f1": 0.7125,
        "cosine_f1_threshold": 0.838166,
        "cosine_precision": 0.620915,
        "cosine_recall": 0.835777,
        "cosine_ap": 0.750355,
        "manhattan_accuracy": 0.682051,
        "manhattan_accuracy_threshold": 12.164995,
        "manhattan_f1": 0.71274,
        "manhattan_f1_threshold": 12.776402,
        "manhattan_precision": 0.60387,
        "manhattan_recall": 0.869501,
        "manhattan_ap": 0.749407,
        "euclidean_accuracy": 0.677656,
        "euclidean_accuracy_threshold": 0.549577,
        "euclidean_f1": 0.7125,
        "euclidean_f1_threshold": 0.568918,
        "euclidean_precision": 0.620915,
        "euclidean_recall": 0.835777,
        "euclidean_ap": 0.750355,
        "dot_accuracy": 0.677656,
        "dot_accuracy_threshold": 0.848983,
        "dot_f1": 0.7125,
        "dot_f1_threshold": 0.838166,
        "dot_precision": 0.620915,
        "dot_recall": 0.835777,
        "dot_ap": 0.750355,
        "max_accuracy": 0.682051,
        "max_f1": 0.71274,
        "max_precision": 0.620915,
        "max_recall": 0.869501,
        "max_ap": 0.750355,
        "main_score": 0.750355,
        "hf_subset": "ru",
        "languages": [
          "rus-Cyrl"
        ]
      },
      {
        "similarity_accuracy": 0.645421,
        "similarity_accuracy_threshold": 0.849971,
        "similarity_f1": 0.697297,
        "similarity_f1_threshold": 0.807301,
        "similarity_precision": 0.552226,
        "similarity_recall": 0.945748,
        "similarity_ap": 0.702325,
        "cosine_accuracy": 0.645421,
        "cosine_accuracy_threshold": 0.849971,
        "cosine_f1": 0.697297,
        "cosine_f1_threshold": 0.807301,
        "cosine_precision": 0.552226,
        "cosine_recall": 0.945748,
        "cosine_ap": 0.702325,
        "manhattan_accuracy": 0.641026,
        "manhattan_accuracy_threshold": 12.046864,
        "manhattan_f1": 0.698257,
        "manhattan_f1_threshold": 13.60284,
        "manhattan_precision": 0.555459,
        "manhattan_recall": 0.939883,
        "manhattan_ap": 0.699631,
        "euclidean_accuracy": 0.645421,
        "euclidean_accuracy_threshold": 0.547775,
        "euclidean_f1": 0.697297,
        "euclidean_f1_threshold": 0.620804,
        "euclidean_precision": 0.552226,
        "euclidean_recall": 0.945748,
        "euclidean_ap": 0.702325,
        "dot_accuracy": 0.645421,
        "dot_accuracy_threshold": 0.849971,
        "dot_f1": 0.697297,
        "dot_f1_threshold": 0.807301,
        "dot_precision": 0.552226,
        "dot_recall": 0.945748,
        "dot_ap": 0.702325,
        "max_accuracy": 0.645421,
        "max_f1": 0.698257,
        "max_precision": 0.555459,
        "max_recall": 0.945748,
        "max_ap": 0.702325,
        "main_score": 0.702325,
        "hf_subset": "sw",
        "languages": [
          "swa-Latn"
        ]
      },
      {
        "similarity_accuracy": 0.657875,
        "similarity_accuracy_threshold": 0.859518,
        "similarity_f1": 0.69874,
        "similarity_f1_threshold": 0.828193,
        "similarity_precision": 0.573308,
        "similarity_recall": 0.894428,
        "similarity_ap": 0.70318,
        "cosine_accuracy": 0.657875,
        "cosine_accuracy_threshold": 0.859518,
        "cosine_f1": 0.69874,
        "cosine_f1_threshold": 0.828193,
        "cosine_precision": 0.573308,
        "cosine_recall": 0.894428,
        "cosine_ap": 0.70318,
        "manhattan_accuracy": 0.657143,
        "manhattan_accuracy_threshold": 11.522882,
        "manhattan_f1": 0.696398,
        "manhattan_f1_threshold": 12.938427,
        "manhattan_precision": 0.570759,
        "manhattan_recall": 0.892962,
        "manhattan_ap": 0.702023,
        "euclidean_accuracy": 0.657875,
        "euclidean_accuracy_threshold": 0.53006,
        "euclidean_f1": 0.69874,
        "euclidean_f1_threshold": 0.586185,
        "euclidean_precision": 0.573308,
        "euclidean_recall": 0.894428,
        "euclidean_ap": 0.70318,
        "dot_accuracy": 0.657875,
        "dot_accuracy_threshold": 0.859518,
        "dot_f1": 0.69874,
        "dot_f1_threshold": 0.828193,
        "dot_precision": 0.573308,
        "dot_recall": 0.894428,
        "dot_ap": 0.70318,
        "max_accuracy": 0.657875,
        "max_f1": 0.69874,
        "max_precision": 0.573308,
        "max_recall": 0.894428,
        "max_ap": 0.70318,
        "main_score": 0.70318,
        "hf_subset": "th",
        "languages": [
          "tha-Thai"
        ]
      },
      {
        "similarity_accuracy": 0.666667,
        "similarity_accuracy_threshold": 0.859736,
        "similarity_f1": 0.704425,
        "similarity_f1_threshold": 0.838474,
        "similarity_precision": 0.589339,
        "similarity_recall": 0.875367,
        "similarity_ap": 0.714957,
        "cosine_accuracy": 0.666667,
        "cosine_accuracy_threshold": 0.859736,
        "cosine_f1": 0.704425,
        "cosine_f1_threshold": 0.838474,
        "cosine_precision": 0.589339,
        "cosine_recall": 0.875367,
        "cosine_ap": 0.714957,
        "manhattan_accuracy": 0.666667,
        "manhattan_accuracy_threshold": 11.3108,
        "manhattan_f1": 0.706444,
        "manhattan_f1_threshold": 12.45729,
        "manhattan_precision": 0.595573,
        "manhattan_recall": 0.868035,
        "manhattan_ap": 0.714009,
        "euclidean_accuracy": 0.666667,
        "euclidean_accuracy_threshold": 0.529648,
        "euclidean_f1": 0.704425,
        "euclidean_f1_threshold": 0.568377,
        "euclidean_precision": 0.589339,
        "euclidean_recall": 0.875367,
        "euclidean_ap": 0.714957,
        "dot_accuracy": 0.666667,
        "dot_accuracy_threshold": 0.859737,
        "dot_f1": 0.704425,
        "dot_f1_threshold": 0.838474,
        "dot_precision": 0.589339,
        "dot_recall": 0.875367,
        "dot_ap": 0.714958,
        "max_accuracy": 0.666667,
        "max_f1": 0.706444,
        "max_precision": 0.595573,
        "max_recall": 0.875367,
        "max_ap": 0.714958,
        "main_score": 0.714958,
        "hf_subset": "tr",
        "languages": [
          "tur-Latn"
        ]
      },
      {
        "similarity_accuracy": 0.678388,
        "similarity_accuracy_threshold": 0.880926,
        "similarity_f1": 0.700467,
        "similarity_f1_threshold": 0.86787,
        "similarity_precision": 0.642595,
        "similarity_recall": 0.769795,
        "similarity_ap": 0.728762,
        "cosine_accuracy": 0.678388,
        "cosine_accuracy_threshold": 0.880926,
        "cosine_f1": 0.700467,
        "cosine_f1_threshold": 0.86787,
        "cosine_precision": 0.642595,
        "cosine_recall": 0.769795,
        "cosine_ap": 0.728762,
        "manhattan_accuracy": 0.680586,
        "manhattan_accuracy_threshold": 10.932602,
        "manhattan_f1": 0.701754,
        "manhattan_f1_threshold": 11.266621,
        "manhattan_precision": 0.65,
        "manhattan_recall": 0.762463,
        "manhattan_ap": 0.727524,
        "euclidean_accuracy": 0.678388,
        "euclidean_accuracy_threshold": 0.488004,
        "euclidean_f1": 0.700467,
        "euclidean_f1_threshold": 0.514062,
        "euclidean_precision": 0.642595,
        "euclidean_recall": 0.769795,
        "euclidean_ap": 0.728762,
        "dot_accuracy": 0.678388,
        "dot_accuracy_threshold": 0.880926,
        "dot_f1": 0.700467,
        "dot_f1_threshold": 0.86787,
        "dot_precision": 0.642595,
        "dot_recall": 0.769795,
        "dot_ap": 0.728762,
        "max_accuracy": 0.680586,
        "max_f1": 0.701754,
        "max_precision": 0.65,
        "max_recall": 0.769795,
        "max_ap": 0.728762,
        "main_score": 0.728762,
        "hf_subset": "vi",
        "languages": [
          "vie-Latn"
        ]
      },
      {
        "similarity_accuracy": 0.671062,
        "similarity_accuracy_threshold": 0.89257,
        "similarity_f1": 0.696812,
        "similarity_f1_threshold": 0.866157,
        "similarity_precision": 0.576222,
        "similarity_recall": 0.881232,
        "similarity_ap": 0.712577,
        "cosine_accuracy": 0.671062,
        "cosine_accuracy_threshold": 0.89257,
        "cosine_f1": 0.696812,
        "cosine_f1_threshold": 0.866157,
        "cosine_precision": 0.576222,
        "cosine_recall": 0.881232,
        "cosine_ap": 0.712577,
        "manhattan_accuracy": 0.671062,
        "manhattan_accuracy_threshold": 10.31613,
        "manhattan_f1": 0.695748,
        "manhattan_f1_threshold": 11.741135,
        "manhattan_precision": 0.558016,
        "manhattan_recall": 0.923754,
        "manhattan_ap": 0.710089,
        "euclidean_accuracy": 0.671062,
        "euclidean_accuracy_threshold": 0.463529,
        "euclidean_f1": 0.696812,
        "euclidean_f1_threshold": 0.517384,
        "euclidean_precision": 0.576222,
        "euclidean_recall": 0.881232,
        "euclidean_ap": 0.712577,
        "dot_accuracy": 0.671062,
        "dot_accuracy_threshold": 0.89257,
        "dot_f1": 0.696812,
        "dot_f1_threshold": 0.866157,
        "dot_precision": 0.576222,
        "dot_recall": 0.881232,
        "dot_ap": 0.712577,
        "max_accuracy": 0.671062,
        "max_f1": 0.696812,
        "max_precision": 0.576222,
        "max_recall": 0.923754,
        "max_ap": 0.712577,
        "main_score": 0.712577,
        "hf_subset": "zh",
        "languages": [
          "zho-Hans"
        ]
      }
    ]
  },
  "evaluation_time": 62.11594271659851,
  "kg_co2_emissions": null
}